rotutils/__init__.py
rotutils/cli.py
rotutils/rotutils.py
rotutils-0.1.0.dist-info/licenses/AUTHORS.rst
rotutils-0.1.0.dist-info/licenses/LICENSE
rotutils-0.1.0.dist-info/METADATA
rotutils-0.1.0.dist-info/WHEEL
rotutils-0.1.0.dist-info/top_level.txt
rotutils-0.1.0.dist-info/RECORD
